apkit/__init__.py
apkit/_version.py
apkit/cache.py
apkit/config.py
apkit/types.py
apkit/abc/server.py
apkit/abc/types.py
apkit/client/__init__.py
apkit/client/_common.py
apkit/client/exceptions.py
apkit/client/models.py
apkit/client/asyncio/__init__.py
apkit/client/asyncio/actor.py
apkit/client/asyncio/client.py
apkit/client/asyncio/types.py
apkit/client/sync/__init__.py
apkit/client/sync/actor.py
apkit/client/sync/client.py
apkit/client/sync/exceptions.py
apkit/client/sync/types.py
apkit/helper/inbox.py
apkit/kv/__init__.py
apkit/kv/inmemory.py
apkit/kv/redis.py
apkit/models/__init__.py
apkit/nodeinfo/__init__.py
apkit/nodeinfo/builder.py
apkit/server/__init__.py
apkit/server/app.py
apkit/server/responses.py
apkit/server/subrouter.py
apkit/server/types.py
apkit/server/routes/inbox.py
apkit/server/routes/nodeinfo.py
apkit/server/routes/outbox.py
apkit-0.3.7.dist-info/METADATA
apkit-0.3.7.dist-info/WHEEL
apkit-0.3.7.dist-info/licenses/LICENSE
apkit-0.3.7.dist-info/RECORD
