Metadata-Version: 2.4
Name: apkit
Version: 0.3.7
Summary: Powerful Toolkit for ActivityPub Implementations.
Project-URL: Repository, https://github.com/fedi-libs/apkit
Project-URL: Issues, https://github.com/fedi-libs/apkit/issues
Project-URL: Changelog, https://github.com/fedi-libs/apkit/blob/main/CHANGELOG.md
Author-email: AmaseCocoa <cocoa@amase.cc>
License-File: LICENSE
Requires-Python: >=3.11
Requires-Dist: aiohttp>=3.12.15
Requires-Dist: apmodel>=0.5.1
Requires-Dist: apsig>=0.6.0
Requires-Dist: charset-normalizer>=3.4.3
Requires-Dist: httpcore[http2,socks]>=1.0.9
Requires-Dist: httpx>=0.28.1
Requires-Dist: requests>=2.32.5
Requires-Dist: types-requests>=2.32.4.20250913
Provides-Extra: redis
Requires-Dist: redis>=5.0.4; extra == 'redis'
Provides-Extra: server
Requires-Dist: fastapi>=0.116.1; extra == 'server'
Requires-Dist: uvicorn>=0.35.0; extra == 'server'
